nplusone/__init__.py
nplusone/base.py
django_nplusone-0.0.5.dist-info/LICENSE
django_nplusone-0.0.5.dist-info/METADATA
django_nplusone-0.0.5.dist-info/WHEEL
django_nplusone-0.0.5.dist-info/top_level.txt
django_nplusone-0.0.5.dist-info/RECORD
