Metadata-Version: 2.1
Name: django-nplusone
Version: 0.0.5
Summary: Discover possible N+1 queries in your code base during development
Home-page: https://github.com/shaffooo/django_nplusone
Author: Shafiq Ur Rahman
Author-email: shafiq.tnoli@gmail.com
License: UNKNOWN
Platform: UNKNOWN
Classifier: License :: OSI Approved :: MIT License
Classifier: Operating System :: OS Independent
Classifier: Intended Audience :: Developers
Classifier: Topic :: Software Development :: Build Tools
Classifier: Programming Language :: Python :: 2
Requires-Python: >=2.7
Requires-Dist: Django (>=1.11.20)
